tmp117.py
circuitpython_tmp117-0.1.2.dist-info/LICENSE
circuitpython_tmp117-0.1.2.dist-info/METADATA
circuitpython_tmp117-0.1.2.dist-info/WHEEL
circuitpython_tmp117-0.1.2.dist-info/top_level.txt
circuitpython_tmp117-0.1.2.dist-info/RECORD
