Metadata-Version: 2.1
Name: circuitpython-tmp117
Version: 0.1.2
Summary: CircuitPython TMP117 Temperature Sensor Low Memory driver
Author-email: JDM <jdm@mozmail.com>
License: MIT
Project-URL: Homepage, https://github.com/jposada202020/CircuitPython_TMP117
Keywords: sensor,circuitpython,tmp117,temperature,TMP117,low,memory,sensor,driver
Classifier: Intended Audience :: Developers
Classifier: Topic :: Software Development :: Libraries
Classifier: Topic :: Software Development :: Embedded Systems
Classifier: Topic :: System :: Hardware
Classifier: License :: OSI Approved :: MIT License
Classifier: Programming Language :: Python :: 3
License-File: LICENSE
Requires-Dist: adafruit-circuitpython-busdevice
Requires-Dist: adafruit-circuitpython-register
Provides-Extra: optional
